Workbook

Sheet README
A1: Sindibad Dummy Correlation Database - Doha Oasis Company
A3: Purpose | B3: Synthetic workbook to feed Sindibad and demonstrate how human capital metrics correlate with finance, brand, customer experience, operations, risk and ISO 30414 readiness.
A5: Sheet | B5: What it contains | C5: How to use it
A6: Employees | B6: 1,000 dummy employee records | C6: Use for workforce segmentation and HR drill-down.
A7: Monthly_HR | B7: Department/month HR facts | C7: Join on Month + Department.
A8: Finance | B8: Department/month finance facts | C8: Correlate cost, revenue, productivity and ROI.
A9: Brand | B9: Department/month brand facts | C9: Correlate engagement, offer acceptance, advocacy and reputation.
A10: Customer_Ops | B10: Department/month customer and operations facts | C10: Correlate training, absence and turnover with service outcomes.
A11: Correlation_Data | B11: Already joined fact table | C11: Best table to import into Sindibad for demo analytics.
A12: Metric_Map | B12: Interpretation library | C12: Use to generate business narrative and recommendations.
A13: Evidence_Readiness | B13: ISO evidence tracker | C13: Use to show audit and accreditation readiness.
A14: Dashboard | B14: Formula-driven summary | C14: Use as a leadership demo page.

Sheet Employees
A1: Employee_ID | B1: Employee_Name | C1: Department | D1: Job_Family | E1: Job_Title | F1: Grade | G1: Contract_Type | H1: Gender | I1: Nationality | J1: Hire_Date | K1: Tenure_Years | L1: Age | M1: Monthly_Salary_QAR | N1: Annual_Workforce_Cost_QAR | O1: Critical_Role | P1: Customer_Facing | Q1: Performance_Score | R1: Engagement_Score | S1: Training_Hours_YTD | T1: Mandatory_Training_Complete | U1: Absence_Days_YTD | V1: Overtime_Hours_YTD | W1: Successor_Ready | X1: High_Performer | Y1: Exit_Risk | Z1: Linked_Business_Unit
A2: DOC-0001 | B2: Nour Nair | C2: IT | D2: Cybersecurity | E2: Cybersecurity G2 | F2: G2 | G2: Permanent | H2: Female | I2: Indian | J2: 41423 | K2: 12.6 | L2: 37 | M2: 7200 | N2: 110602 | O2: No | P2: Yes | Q2: 3.55 | R2: 74 | S2: 24 | T2: Yes | U2: 0 | V2: 10 | W2: N/A | X2: Yes | Y2: Low | Z2: IT
A3: DOC-0002 | B3: Lina Singh | C3: Facilities | D3: Maintenance | E3: Maintenance G4 | F3: G4 | G3: Permanent | H3: Male | I3: Lebanese | J3: 44423 | K3: 4.4 | L3: 26 | M3: 11800 | N3: 182950 | O3: No | P3: No | Q3: 3.2 | R3: 81 | S3: 36 | T3: No | U3: 5 | V3: 0 | W3: N/A | X3: No | Y3: Low | Z3: Facilities
A4: DOC-0003 | B4: Sara Hassan | C4: Finance | D4: Accounting | E4: Accounting M1 | F4: M1 | G4: Fixed-term | H4: Female | I4: Indian | J4: 41471 | K4: 12.5 | L4: 29 | M4: 17100 | N4: 276124 | O4: Yes | P4: No | Q4: 3.49 | R4: 58 | S4: 42 | T4: Yes | U4: 5 | V4: 35 | W4: Yes | X4: No | Y4: Medium | Z4: Finance
A5: DOC-0004 | B5: Maya Youssef | C5: Hospitality | D5: Guest Services | E5: Guest Services G1 | F5: G1 | G5: Permanent | H5: Male | I5: Egyptian | J5: 42448 | K5: 9.8 | L5: 29 | M5: 4400 | N5: 68247 | O5: No | P5: Yes | Q5: 3.58 | R5: 56 | S5: 7 | T5: Yes | U5: 8 | V5: 47 | W5: N/A | X5: Yes | Y5: Medium | Z5: Hospitality
A6: DOC-0005 | B6: Lina Ali | C6: Operations | D6: Planning | E6: Planning G4 | F6: G4 | G6: Permanent | H6: Male | I6: Qatari | J6: 45775 | K6: 0.7 | L6: 22 | M6: 11100 | N6: 169597 | O6: No | P6: Yes | Q6: 3.72 | R6: 74 | S6: 25 | T6: Yes | U6: 5 | V6: 24 | W6: N/A | X6: Yes | Y6: Low | Z6: Operations
A7: DOC-0006 | B7: Maya Mansour | C7: Retail | D7: Sales | E7: Sales G1 | F7: G1 | G7: Fixed-term | H7: Male | I7: Tunisian | J7: 41270 | K7: 13 | L7: 60 | M7: 3800 | N7: 59264 | O7: No | P7: Yes | Q7: 3.32 | R7: 55 | S7: 28 | T7: Yes | U7: 3 | V7: 65 | W7: N/A | X7: No | Y7: Medium | Z7: Retail
A8: DOC-0007 | B8: Priya Rahman | C8: Security | D8: Security Operations | E8: Security Operations G1 | F8: G1 | G8: Permanent | H8: Female | I8: Nepali | J8: 45098 | K8: 2.5 | L8: 54 | M8: 4500 | N8: 68311 | O8: No | P8: Yes | Q8: 3.23 | R8: 62 | S8: 17 | T8: Yes | U8: 0 | V8: 23 | W8: N/A | X8: No | Y8: Medium | Z8: Security
A9: DOC-0008 | B9: Lea Ibrahim | C9: Operations | D9: Planning | E9: Planning M1 | F9: M1 | G9: Permanent | H9: Female | I9: Jordanian | J9: 43344 | K9: 7.3 | L9: 42 | M9: 22600 | N9: 372637 | O9: Yes | P9: Yes | Q9: 2.65 | R9: 63 | S9: 0 | T9: Yes | U9: 5 | V9: 0 | W9: No | X9: No | Y9: Low | Z9: Operations
A10: DOC-0009 | B10: Noor Singh | C10: Facilities | D10: Cleaning | E10: Cleaning G3 | F10: G3 | G10: Fixed-term | H10: Male | I10: Pakistani | J10: 43747 | K10: 6.2 | L10: 28 | M10: 9100 | N10: 145925 | O10: Yes | P10: No | Q10: 3.39 | R10: 57 | S10: 17 | T10: Yes | U10: 6 | V10: 31 | W10: No | X10: No | Y10: Medium | Z10: Facilities
A11: DOC-0010 | B11: Priya Ibrahim | C11: HR | D11: Recruitment | E11: Recruitment G2 | F11: G2 | G11: Permanent | H11: Male | I11: Qatari | J11: 41769 | K11: 11.7 | L11: 59 | M11: 6800 | N11: 107750 | O11: No | P11: No | Q11: 3 | R11: 52 | S11: 10 | T11: Yes | U11: 5 | V11: 1 | W11: N/A | X11: No | Y11: Medium | Z11: HR
A12: DOC-0011 | B12: Priya Patel | C12: Operations | D12: Operations Management | E12: Operations Management G3 | F12: G3 | G12: Permanent | H12: Male | I12: Egyptian | J12: 45679 | K12: 0.9 | L12: 38 | M12: 9500 | N12: 148956 | O12: No | P12: Yes | Q12: 2.09 | R12: 45 | S12: 21 | T12: Yes | U12: 0 | V12: 0 | W12: N/A | X12: No | Y12: Medium | Z12: Operations
A13: DOC-0012 | B13: Hana Nair | C13: Marketing | D13: Digital Marketing | E13: Digital Marketing G5 | F13: G5 | G13: Permanent | H13: Male | I13: Indian | J13: 44112 | K13: 5.2 | L13: 34 | M13: 12000 | N13: 186209 | O13: No | P13: No | Q13: 3.09 | R13: 67 | S13: 14 | T13: Yes | U13: 6 | V13: 0 | W13: N/A | X13: No | Y13: Low | Z13: Marketing
... A1001: DOC-1000 | B1001: Sara Singh | C1001: IT | D1001: Applications | E1001: Applications G2 | F1001: G2 | G1001: Permanent | H1001: Female | I1001: Indian | J1001: 41862 | K1001: 11.4 | L1001: 26 | M1001: 5700 | N1001: 83084 | O1001: No | P1001: No | Q1001: 2.36 | R1001: 63 | S1001: 21 | T1001: Yes | U1001: 0 | V1001: 8 | W1001: N/A | X1001: No | Y1001: Low | Z1001: IT

Sheet Monthly_HR
A1: Month | B1: Department | C1: Opening_Headcount | D1: Hires | E1: Leavers | F1: Average_Headcount | G1: Vacancies | H1: Voluntary_Leavers | I1: Critical_Role_Leavers | J1: Absence_Days | K1: Available_Workdays | L1: Training_Completion_Rate | M1: Engagement_Score | N1: Policy_Acknowledgement_Rate | O1: Mandatory_Training_Completion | P1: Succession_Coverage | Q1: Turnover_Rate | R1: Absence_Rate | S1: Vacancy_Rate
A2: 45658 | B2: Hospitality | C2: 165 | D2: 7 | E2: 4 | F2: 166 | G2: 11 | H2: 3 | I2: 0 | J2: 99 | K2: 3652 | L2: 0.85942998 | M2: 65 | N2: 0.9003686 | O2: 0.8412354 | P2: 0.46391998 | Q2: 0.024096386 | R2: 0.027108434 | S2: 0.062146893
A3: 45689 | B3: Hospitality | C3: 168 | D3: 4 | E3: 3 | F3: 168 | G3: 11 | H3: 2 | I3: 0 | J3: 56 | K3: 3696 | L3: 0.83529953 | M3: 52 | N3: 0.90911024 | O3: 0.81031439 | P3: 0.67296753 | Q3: 0.017857143 | R3: 0.015151515 | S3: 0.061452514
A4: 45717 | B4: Hospitality | C4: 169 | D4: 3 | E4: 4 | F4: 168 | G4: 9 | H4: 3 | I4: 0 | J4: 85 | K4: 3696 | L4: 0.72626061 | M4: 51 | N4: 0.94780397 | O4: 0.79540259 | P4: 0.42483502 | Q4: 0.023809524 | R4: 0.022997835 | S4: 0.050847458
A5: 45748 | B5: Hospitality | C5: 168 | D5: 5 | E5: 3 | F5: 169 | G5: 6 | H5: 2 | I5: 0 | J5: 68 | K5: 3718 | L5: 0.82935836 | M5: 61 | N5: 0.95881638 | O5: 0.90864086 | P5: 0.83136157 | Q5: 0.017751479 | R5: 0.018289403 | S5: 0.034285714
A6: 45778 | B6: Hospitality | C6: 170 | D6: 3 | E6: 4 | F6: 170 | G6: 9 | H6: 2 | I6: 0 | J6: 84 | K6: 3740 | L6: 0.7578254 | M6: 62 | N6: 0.99762526 | O6: 0.71000074 | P6: 0.47857896 | Q6: 0.023529412 | R6: 0.022459893 | S6: 0.05027933
A7: 45809 | B7: Hospitality | C7: 169 | D7: 3 | E7: 3 | F7: 169 | G7: 13 | H7: 2 | I7: 0 | J7: 57 | K7: 3718 | L7: 0.83911526 | M7: 67 | N7: 0.94692453 | O7: 0.9130329 | P7: 0.57977514 | Q7: 0.017751479 | R7: 0.015330823 | S7: 0.071428571
A8: 45839 | B8: Hospitality | C8: 169 | D8: 1 | E8: 4 | F8: 168 | G8: 6 | H8: 2 | I8: 0 | J8: 98 | K8: 3696 | L8: 0.83836235 | M8: 65 | N8: 0.8743995 | O8: 0.82148619 | P8: 0.63191056 | Q8: 0.023809524 | R8: 0.026515152 | S8: 0.034482759
A9: 45870 | B9: Hospitality | C9: 166 | D9: 3 | E9: 4 | F9: 166 | G9: 11 | H9: 2 | I9: 0 | J9: 56 | K9: 3652 | L9: 0.70956321 | M9: 71 | N9: 0.97161176 | O9: 0.68 | P9: 0.78377349 | Q9: 0.024096386 | R9: 0.015334064 | S9: 0.062146893
A10: 45901 | B10: Hospitality | C10: 165 | D10: 0 | E10: 3 | F10: 164 | G10: 6 | H10: 2 | I10: 0 | J10: 78 | K10: 3608 | L10: 0.85182831 | M10: 70 | N10: 0.87239131 | O10: 0.86512259 | P10: 0.58391344 | Q10: 0.018292683 | R10: 0.021618625 | S10: 0.035294118
A11: 45931 | B11: Hospitality | C11: 162 | D11: 1 | E11: 3 | F11: 161 | G11: 11 | H11: 2 | I11: 0 | J11: 92 | K11: 3542 | L11: 0.78802905 | M11: 59 | N11: 0.90015846 | O11: 0.82377181 | P11: 0.55635781 | Q11: 0.01863354 | R11: 0.025974026 | S11: 0.063953488
A12: 45962 | B12: Hospitality | C12: 160 | D12: 3 | E12: 2 | F12: 160 | G12: 10 | H12: 1 | I12: 0 | J12: 61 | K12: 3520 | L12: 0.79163342 | M12: 68 | N12: 0.93652067 | O12: 0.7513736 | P12: 0.71820427 | Q12: 0.0125 | R12: 0.017329545 | S12: 0.058823529
A13: 45992 | B13: Hospitality | C13: 161 | D13: 2 | E13: 4 | F13: 160 | G13: 8 | H13: 2 | I13: 0 | J13: 65 | K13: 3520 | L13: 0.8439862 | M13: 66 | N13: 0.99583247 | O13: 0.80442172 | P13: 0.55679752 | Q13: 0.025 | R13: 0.018465909 | S13: 0.047619048
... A121: 45992 | B121: Customer Experience | C121: 76 | D121: 3 | E121: 2 | F121: 76 | G121: 0 | H121: 1 | I121: 0 | J121: 33 | K121: 1672 | L121: 0.74388365 | M121: 45 | N121: 0.91689762 | O121: 0.73781683 | P121: 0.44159193 | Q121: 0.026315789 | R121: 0.019736842 | S121: 0

Sheet Finance
A1: Month | B1: Department | C1: Revenue_QAR | D1: Operating_Cost_Excl_Workforce_QAR | E1: Workforce_Cost_QAR | F1: Overtime_Cost_QAR | G1: Training_Cost_QAR | H1: Recruitment_Cost_QAR | I1: Turnover_Cost_QAR | J1: Output_Index | K1: Revenue_Per_Employee | L1: Workforce_Cost_Ratio | M1: Human_Capital_ROI
A2: 45658 | B2: Hospitality | C2: 1557180 | D2: 902490 | E2: 2286671 | F2: 157315 | G2: 58137 | H2: 58410 | I2: 132372 | J2: 86.7 | K2: 9380.6024 | L2: 1.4684693 | M2: 0.28630704
A3: 45689 | B3: Hospitality | C3: 1734891 | D3: 996191 | E3: 2314221 | F3: 122802 | G3: 62219 | H3: 25890 | I3: 124884 | J3: 81.7 | K3: 10326.732 | L3: 1.3339288 | M3: 0.31920028
A4: 45717 | B4: Hospitality | C4: 1622235 | D4: 806202 | E4: 2314221 | F4: 129559 | G4: 116982 | H4: 14998 | I4: 137770 | J4: 80.3 | K4: 9656.1607 | L4: 1.4265634 | M4: 0.35261671
A5: 45748 | B5: Hospitality | C5: 1710177 | D5: 951701 | E5: 2327996 | F5: 127091 | G5: 67595 | H5: 42510 | I5: 115222 | J5: 82.9 | K5: 10119.391 | L5: 1.3612603 | M5: 0.3258064
A6: 45778 | B6: Hospitality | C6: 1715575 | D6: 733712 | E6: 2341771 | F6: 132803 | G6: 54347 | H6: 24992 | I6: 121108 | J6: 79.9 | K6: 10091.618 | L6: 1.3650065 | M6: 0.41928224
A7: 45809 | B7: Hospitality | C7: 1645344 | D7: 801503 | E7: 2327996 | F7: 123622 | G7: 142055 | H7: 21437 | I7: 128172 | J7: 85.7 | K7: 9735.7633 | L7: 1.4148993 | M7: 0.36247528
A8: 45839 | B8: Hospitality | C8: 1699882 | D8: 817616 | E8: 2314221 | F8: 129892 | G8: 117569 | H8: 6205 | I8: 175177 | J8: 87.3 | K8: 10118.345 | L8: 1.361401 | M8: 0.38123671
A9: 45870 | B9: Hospitality | C9: 1499941 | D9: 805292 | E9: 2286671 | F9: 123352 | G9: 127419 | H9: 15609 | I9: 89140 | J9: 90 | K9: 9035.7892 | L9: 1.5245073 | M9: 0.30378179
A10: 45901 | B10: Hospitality | C10: 1625663 | D10: 826356 | E10: 2259120 | F10: 118793 | G10: 109028 | H10: 0 | I10: 66932 | J10: 90.4 | K10: 9912.5793 | L10: 1.3896607 | M10: 0.35381343
A11: 45931 | B11: Hospitality | C11: 1402640 | D11: 759480 | E11: 2217795 | F11: 144750 | G11: 106782 | H11: 4872 | I11: 83516 | J11: 83.4 | K11: 8712.0497 | L11: 1.5811577 | M11: 0.28999975
A12: 45962 | B12: Hospitality | C12: 1538569 | D12: 846643 | E12: 2204020 | F12: 120869 | G12: 71496 | H12: 22527 | I12: 55980 | J12: 87 | K12: 9616.0562 | L12: 1.4325129 | M12: 0.31393817
A13: 45992 | B13: Hospitality | C13: 1502620 | D13: 604608 | E13: 2204020 | F13: 119816 | G13: 117386 | H13: 11712 | I13: 170942 | J13: 82.9 | K13: 9391.375 | L13: 1.4667847 | M13: 0.40744276
... A121: 45992 | B121: Customer Experience | C121: 658043 | D121: 348425 | E121: 1221915 | F121: 57367 | G121: 37131 | H121: 14897 | I121: 74100 | J121: 81.5 | K121: 8658.4605 | L121: 1.8568923 | M121: 0.25338751

Sheet Brand
A1: Month | B1: Department | C1: Offer_Acceptance_Rate | D1: Candidate_NPS | E1: Employer_Brand_Score | F1: Employee_Advocacy_Score | G1: Social_Sentiment_Score | H1: Brand_Campaign_Reach | I1: Glassdoor_Style_Rating
A2: 45658 | B2: Hospitality | C2: 0.6308583 | D2: 7 | E2: 63 | F2: 67 | G2: 79 | H2: 12529 | I2: 3.9
A3: 45689 | B3: Hospitality | C3: 0.68120294 | D3: 41 | E3: 64 | F3: 58 | G3: 72 | H3: 60716 | I3: 4.1
A4: 45717 | B4: Hospitality | C4: 0.66939215 | D4: 40 | E4: 55 | F4: 39 | G4: 64 | H4: 13210 | I4: 4.1
A5: 45748 | B5: Hospitality | C5: 0.7006651 | D5: 40 | E5: 67 | F5: 65 | G5: 73 | H5: 17710 | I5: 3.5
A6: 45778 | B6: Hospitality | C6: 0.77373537 | D6: 38 | E6: 71 | F6: 68 | G6: 77 | H6: 45663 | I6: 3.6
A7: 45809 | B7: Hospitality | C7: 0.77812405 | D7: 30 | E7: 68 | F7: 72 | G7: 69 | H7: 26936 | I7: 4
A8: 45839 | B8: Hospitality | C8: 0.64044387 | D8: 40 | E8: 64 | F8: 58 | G8: 73 | H8: 34476 | I8: 3.5
A9: 45870 | B9: Hospitality | C9: 0.71898993 | D9: 25 | E9: 65 | F9: 64 | G9: 73 | H9: 54594 | I9: 3.8
A10: 45901 | B10: Hospitality | C10: 0.85102144 | D10: 50 | E10: 71 | F10: 70 | G10: 64 | H10: 30734 | I10: 3.8
A11: 45931 | B11: Hospitality | C11: 0.60780317 | D11: 31 | E11: 57 | F11: 50 | G11: 68 | H11: 53368 | I11: 3.7
A12: 45962 | B12: Hospitality | C12: 0.64270645 | D12: 29 | E12: 62 | F12: 58 | G12: 72 | H12: 60655 | I12: 3.9
A13: 45992 | B13: Hospitality | C13: 0.63268998 | D13: 31 | E13: 66 | F13: 64 | G13: 78 | H13: 56859 | I13: 3.9
... A121: 45992 | B121: Customer Experience | C121: 0.4969603 | D121: 8 | E121: 52 | F121: 48 | G121: 71 | H121: 35871 | I121: 3.8

Sheet Customer_Ops
A1: Month | B1: Department | C1: Customer_Satisfaction | D1: Complaint_Rate | E1: SLA_Compliance | F1: Service_Backlog | G1: Quality_Incidents | H1: Response_Time_Hours | I1: Operational_Risk_Score
A2: 45658 | B2: Hospitality | C2: 85 | D2: 11.32 | E2: 0.89015404 | F2: 319 | G2: 2 | H2: 4.4 | I2: 53
A3: 45689 | B3: Hospitality | C3: 79 | D3: 10.76 | E3: 0.79846426 | F3: 241 | G3: 3 | H3: 6 | I3: 57
A4: 45717 | B4: Hospitality | C4: 74 | D4: 13.59 | E4: 0.79212382 | F4: 263 | G4: 3 | H4: 4.9 | I4: 58
A5: 45748 | B5: Hospitality | C5: 71 | D5: 11.91 | E5: 0.81998816 | F5: 158 | G5: 4 | H5: 4.6 | I5: 53
A6: 45778 | B6: Hospitality | C6: 80 | D6: 11.93 | E6: 0.83394451 | F6: 387 | G6: 2 | H6: 5.1 | I6: 54
A7: 45809 | B7: Hospitality | C7: 77 | D7: 11.48 | E7: 0.84239767 | F7: 385 | G7: 4 | H7: 5.8 | I7: 55
A8: 45839 | B8: Hospitality | C8: 73 | D8: 13.56 | E8: 0.83197367 | F8: 301 | G8: 2 | H8: 4.9 | I8: 53
A9: 45870 | B9: Hospitality | C9: 75 | D9: 13.71 | E9: 0.79287151 | F9: 202 | G9: 3 | H9: 5.4 | I9: 58
A10: 45901 | B10: Hospitality | C10: 83 | D10: 12.05 | E10: 0.8725671 | F10: 165 | G10: 4 | H10: 5.1 | I10: 50
A11: 45931 | B11: Hospitality | C11: 73 | D11: 12.02 | E11: 0.78204906 | F11: 187 | G11: 2 | H11: 6 | I11: 60
A12: 45962 | B12: Hospitality | C12: 75 | D12: 11.02 | E12: 0.78607313 | F12: 210 | G12: 4 | H12: 5.9 | I12: 57
A13: 45992 | B13: Hospitality | C13: 78 | D13: 10.69 | E13: 0.82479171 | F13: 221 | G13: 3 | H13: 5.7 | I13: 54
... A121: 45992 | B121: Customer Experience | C121: 73 | D121: 9.87 | E121: 0.84623099 | F121: 74 | G121: 2 | H121: 3.7 | I121: 47

Sheet Correlation_Data
A1: Month | B1: Department | C1: Turnover_Rate | D1: Absence_Rate | E1: Vacancy_Rate | F1: Training_Completion_Rate | G1: Engagement_Score | H1: Succession_Coverage | I1: Workforce_Cost_QAR | J1: Revenue_QAR | K1: Revenue_Per_Employee | L1: Human_Capital_ROI | M1: Employer_Brand_Score | N1: Offer_Acceptance_Rate | O1: Customer_Satisfaction | P1: Complaint_Rate | Q1: SLA_Compliance | R1: Service_Backlog | S1: Operational_Risk_Score | T1: Composite_HC_Impact_Score
A2: 45658 | B2: Hospitality | C2: 0.024096386 | D2: 0.027108434 | E2: 0.062146893 | F2: 0.85942998 | G2: 65 | H2: 0.46391998 | I2: 2286671 | J2: 1557180 | K2: 9380.6024 | L2: 0.28630704 | M2: 63 | N2: 0.6308583 | O2: 85 | P2: 11.32 | Q2: 0.89015404 | R2: 319 | S2: 53 | T2: 77.5
A3: 45689 | B3: Hospitality | C3: 0.017857143 | D3: 0.015151515 | E3: 0.061452514 | F3: 0.83529953 | G3: 52 | H3: 0.67296753 | I3: 2314221 | J3: 1734891 | K3: 10326.732 | L3: 0.31920028 | M3: 64 | N3: 0.68120294 | O3: 79 | P3: 10.76 | Q3: 0.79846426 | R3: 241 | S3: 57 | T3: 78.1
A4: 45717 | B4: Hospitality | C4: 0.023809524 | D4: 0.022997835 | E4: 0.050847458 | F4: 0.72626061 | G4: 51 | H4: 0.42483502 | I4: 2314221 | J4: 1622235 | K4: 9656.1607 | L4: 0.35261671 | M4: 55 | N4: 0.66939215 | O4: 74 | P4: 13.59 | Q4: 0.79212382 | R4: 263 | S4: 58 | T4: 71.5
A5: 45748 | B5: Hospitality | C5: 0.017751479 | D5: 0.018289403 | E5: 0.034285714 | F5: 0.82935836 | G5: 61 | H5: 0.83136157 | I5: 2327996 | J5: 1710177 | K5: 10119.391 | L5: 0.3258064 | M5: 67 | N5: 0.7006651 | O5: 71 | P5: 11.91 | Q5: 0.81998816 | R5: 158 | S5: 53 | T5: 81.5
A6: 45778 | B6: Hospitality | C6: 0.023529412 | D6: 0.022459893 | E6: 0.05027933 | F6: 0.7578254 | G6: 62 | H6: 0.47857896 | I6: 2341771 | J6: 1715575 | K6: 10091.618 | L6: 0.41928224 | M6: 71 | N6: 0.77373537 | O6: 80 | P6: 11.93 | Q6: 0.83394451 | R6: 387 | S6: 54 | T6: 75.5
A7: 45809 | B7: Hospitality | C7: 0.017751479 | D7: 0.015330823 | E7: 0.071428571 | F7: 0.83911526 | G7: 67 | H7: 0.57977514 | I7: 2327996 | J7: 1645344 | K7: 9735.7633 | L7: 0.36247528 | M7: 68 | N7: 0.77812405 | O7: 77 | P7: 11.48 | Q7: 0.84239767 | R7: 385 | S7: 55 | T7: 80.5
A8: 45839 | B8: Hospitality | C8: 0.023809524 | D8: 0.026515152 | E8: 0.034482759 | F8: 0.83836235 | G8: 65 | H8: 0.63191056 | I8: 2314221 | J8: 1699882 | K8: 10118.345 | L8: 0.38123671 | M8: 64 | N8: 0.64044387 | O8: 73 | P8: 13.56 | Q8: 0.83197367 | R8: 301 | S8: 53 | T8: 78.6
A9: 45870 | B9: Hospitality | C9: 0.024096386 | D9: 0.015334064 | E9: 0.062146893 | F9: 0.70956321 | G9: 71 | H9: 0.78377349 | I9: 2286671 | J9: 1499941 | K9: 9035.7892 | L9: 0.30378179 | M9: 65 | N9: 0.71898993 | O9: 75 | P9: 13.71 | Q9: 0.79287151 | R9: 202 | S9: 58 | T9: 80.7
A10: 45901 | B10: Hospitality | C10: 0.018292683 | D10: 0.021618625 | E10: 0.035294118 | F10: 0.85182831 | G10: 70 | H10: 0.58391344 | I10: 2259120 | J10: 1625663 | K10: 9912.5793 | L10: 0.35381343 | M10: 71 | N10: 0.85102144 | O10: 83 | P10: 12.05 | Q10: 0.8725671 | R10: 165 | S10: 50 | T10: 80.8
A11: 45931 | B11: Hospitality | C11: 0.01863354 | D11: 0.025974026 | E11: 0.063953488 | F11: 0.78802905 | G11: 59 | H11: 0.55635781 | I11: 2217795 | J11: 1402640 | K11: 8712.0497 | L11: 0.28999975 | M11: 57 | N11: 0.60780317 | O11: 73 | P11: 12.02 | Q11: 0.78204906 | R11: 187 | S11: 60 | T11: 75.5
A12: 45962 | B12: Hospitality | C12: 0.0125 | D12: 0.017329545 | E12: 0.058823529 | F12: 0.79163342 | G12: 68 | H12: 0.71820427 | I12: 2204020 | J12: 1538569 | K12: 9616.0562 | L12: 0.31393817 | M12: 62 | N12: 0.64270645 | O12: 75 | P12: 11.02 | Q12: 0.78607313 | R12: 210 | S12: 57 | T12: 81
A13: 45992 | B13: Hospitality | C13: 0.025 | D13: 0.018465909 | E13: 0.047619048 | F13: 0.8439862 | G13: 66 | H13: 0.55679752 | I13: 2204020 | J13: 1502620 | K13: 9391.375 | L13: 0.40744276 | M13: 66 | N13: 0.63268998 | O13: 78 | P13: 10.69 | Q13: 0.82479171 | R13: 221 | S13: 54 | T13: 79
... A121: 45992 | B121: Customer Experience | C121: 0.026315789 | D121: 0.019736842 | E121: 0 | F121: 0.74388365 | G121: 45 | H121: 0.44159193 | I121: 1221915 | J121: 658043 | K121: 8658.4605 | L121: 0.25338751 | M121: 52 | N121: 0.4969603 | O121: 73 | P121: 9.87 | Q121: 0.84623099 | R121: 74 | S121: 47 | T121: 71.8

Sheet Metric_Map
A1: Business Area | B1: Business KPI | C1: Human Capital Driver | D1: Correlation Logic | E1: Sindibad Insight Example | F1: Suggested Action
A2: Finance | B2: Revenue per employee | C2: Engagement Score | D2: Higher engagement should support stronger productivity and revenue per employee. | E2: Low engagement and falling revenue per employee indicate productivity risk. | F2: Review manager capability, workload and recognition.
A3: Finance | B3: Overtime Cost | C3: Absence Rate + Vacancy Rate | D3: High absence and vacancies usually create overtime pressure. | E3: Rising absence and vacancies explain overtime cost increase. | F3: Strengthen workforce planning and absence management.
A4: Finance | B4: Turnover Cost | C4: Turnover Rate | D4: Leavers create replacement, recruitment and onboarding cost. | E4: High turnover is creating hidden cost pressure. | F4: Create retention plan for high-risk roles.
A5: Brand | B5: Employer Brand Score | C5: Engagement + Offer Acceptance | D5: Candidate and employee perceptions move together. | E5: Low engagement and offer acceptance signal EVP weakness. | F5: Refresh employer value proposition.
A6: Customer | B6: Customer Satisfaction | C6: Training Completion + Engagement | D6: Prepared and engaged staff usually serve customers better. | E6: Low training completion aligns with lower customer satisfaction. | F6: Focus training on customer-facing roles.
A7: Customer | B7: Complaint Rate | C7: Turnover + Absence | D7: Unstable teams often create service inconsistency. | E7: High turnover and absence are linked with more complaints. | F7: Stabilise rosters and improve onboarding.
A8: Operations | B8: SLA Compliance | C8: Vacancy + Skills Gap | D8: Missing roles and skills reduce service speed. | E8: Vacancies are lowering SLA compliance. | F8: Prioritise critical recruitment and cross-training.
A9: Risk | B9: Compliance Readiness | C9: Policy Acknowledgement + Mandatory Training | D9: Weak completion creates audit exposure. | E9: Incomplete policy acknowledgement is an evidence gap. | F9: Automate reminders and escalation.
A10: ESG | B10: Localisation / Qatarisation | C10: Workforce Composition + Development | D10: Local talent pipelines support national contribution. | E10: Low leadership localisation shows succession gap. | F10: Build Qatari leadership pipeline.
A11: Strategy | B11: Human Capital Impact Score | C11: Turnover + engagement + skills + succession | D11: A combined score shows people risk to business strategy. | E11: Low impact score flags departments needing leadership attention. | F11: Assign corrective action owner.

Sheet Evidence_Readiness
A1: ISO Area | B1: Owner | C1: Source System | D1: Evidence Required | E1: Completeness % | F1: Validation Status | G1: Risk Level | H1: Next Action
A2: Workforce Composition | B2: HR Operations | C2: HRMS | D2: Employee master data extract | E2: 0.96 | F2: Validated | G2: Low | H2: Monthly HRMS data check
A3: Recruitment | B3: Talent Acquisition | C3: ATS / Excel | D3: Vacancy approval, source of hire, offer records | E3: 0.78 | F3: Partially Validated | G3: Medium | H3: Standardise recruitment tracker
A4: Turnover | B4: HR Operations | C4: HRMS / Exit Forms | D4: Leaver report, exit reason summary | E4: 0.82 | F4: Partially Validated | G4: Medium | H4: Clean exit reason categories
A5: Skills & Development | B5: L&D | C5: LMS | D5: Attendance, completion, certificates, impact survey | E5: 0.7 | F5: In Progress | G5: High | H5: Add impact measurement
A6: Succession | B6: Talent Management | C6: Talent File | D6: Critical role list, successors, readiness levels | E6: 0.58 | F6: In Progress | G6: High | H6: Build successor readiness register
A7: Workforce Cost | B7: Finance | C7: Payroll / GL | D7: Payroll extract, benefits, workforce cost validation | E7: 0.91 | F7: Validated | G7: Low | H7: Quarterly finance reconciliation
A8: Productivity | B8: Strategy / Finance | C8: Finance / Ops | D8: Revenue, output, headcount and productivity logic | E8: 0.74 | F8: Partially Validated | G8: Medium | H8: Agree productivity formulas
A9: Engagement & Culture | B9: HR / Marketing | C9: Survey Platform | D9: Engagement report, action plan, communication evidence | E9: 0.86 | F9: Validated | G9: Low | H9: Link actions to departments
A10: Compliance & Ethics | B10: ER / Legal | C10: Case Management | D10: Policy acknowledgement, ER case log, corrective actions | E10: 0.8 | F10: Partially Validated | G10: Medium | H10: Improve case closure evidence
A11: Health & Wellbeing | B11: HR / HSE | C11: HSE / Absence | D11: Sick leave, incidents, wellbeing participation | E11: 0.76 | F11: Partially Validated | G11: Medium | H11: Integrate HSE records
A12: Brand Correlation | B12: Marketing / HR | C12: Survey / Campaign Data | D12: EVP metrics, advocacy, sentiment, offer acceptance | E12: 0.62 | F12: In Progress | G12: High | H12: Connect candidate and employee brand data
A13: Customer Correlation | B13: Customer Experience | C13: CRM / Service Desk | D13: CSAT, complaints, SLA, response time | E13: 0.68 | F13: In Progress | G13: High | H13: Map frontline teams to service results

Sheet Dashboard
A1: Sindibad Human Capital Correlation Dashboard - Doha Oasis Company
A3: KPI | B3: Value | D3: Correlation Pair | E3: Excel Formula | F3: Value
A4: Average Engagement Score | B4: =AVERAGE(Correlation_Data!G2:G121) -> 64.9 | D4: Engagement vs Revenue / Employee | E4: =CORREL(Correlation_Data!G2:G121,Correlation_Data!K2:K121) -> -0.14836385 | F4: =CORREL(Correlation_Data!G2:G121,Correlation_Data!K2:K121) -> -0.14836385
A5: Average Turnover Rate | B5: =AVERAGE(Correlation_Data!C2:C121) -> 0.017444656 | D5: Engagement vs Employer Brand | E5: =CORREL(Correlation_Data!G2:G121,Correlation_Data!M2:M121) -> 0.76904194 | F5: =CORREL(Correlation_Data!G2:G121,Correlation_Data!M2:M121) -> 0.76904194
A6: Average Absence Rate | B6: =AVERAGE(Correlation_Data!D2:D121) -> 0.023857835 | D6: Training Completion vs Customer Satisfaction | E6: =CORREL(Correlation_Data!F2:F121,Correlation_Data!O2:O121) -> 0.39585352 | F6: =CORREL(Correlation_Data!F2:F121,Correlation_Data!O2:O121) -> 0.39585352
A7: Average Training Completion | B7: =AVERAGE(Correlation_Data!F2:F121) -> 0.80742836 | D7: Turnover Rate vs Complaint Rate | E7: =CORREL(Correlation_Data!C2:C121,Correlation_Data!P2:P121) -> 0.32385188 | F7: =CORREL(Correlation_Data!C2:C121,Correlation_Data!P2:P121) -> 0.32385188
A8: Average Employer Brand Score | B8: =AVERAGE(Correlation_Data!M2:M121) -> 65.6 | D8: Absence Rate vs SLA Compliance | E8: =CORREL(Correlation_Data!D2:D121,Correlation_Data!Q2:Q121) -> -0.11070889 | F8: =CORREL(Correlation_Data!D2:D121,Correlation_Data!Q2:Q121) -> -0.11070889
A9: Average Customer Satisfaction | B9: =AVERAGE(Correlation_Data!O2:O121) -> 74.358333 | D9: Vacancy Rate vs Service Backlog | E9: =CORREL(Correlation_Data!E2:E121,Correlation_Data!R2:R121) -> 0.25061791 | F9: =CORREL(Correlation_Data!E2:E121,Correlation_Data!R2:R121) -> 0.25061791
A10: Average SLA Compliance | B10: =AVERAGE(Correlation_Data!Q2:Q121) -> 0.8063831 | D10: HC Impact Score vs Human Capital ROI | E10: =CORREL(Correlation_Data!T2:T121,Correlation_Data!L2:L121) -> -0.0078244347 | F10: =CORREL(Correlation_Data!T2:T121,Correlation_Data!L2:L121) -> -0.0078244347
A11: Average HC Impact Score | B11: =AVERAGE(Correlation_Data!T2:T121) -> 78.450833
A12: Total Revenue QAR | B12: =SUM(Correlation_Data!J2:J121) -> 79033312
A13: Total Workforce Cost QAR | B13: =SUM(Correlation_Data!I2:I121) -> 180439995
A16: Department | B16: Engagement | C16: Turnover | D16: Training | E16: Brand | F16: CSAT | G16: SLA | H16: HC Impact
A17: Hospitality | B17: =AVERAGEIFS(Correlation_Data!G:G,Correlation_Data!B:B,A17) -> 63.083333 | C17: =AVERAGEIFS(Correlation_Data!C:C,Correlation_Data!B:B,A17) -> 0.020593963 | D17: =AVERAGEIFS(Correlation_Data!F:F,Correlation_Data!B:B,A17) -> 0.80589097 | E17: =AVERAGEIFS(Correlation_Data!M:M,Correlation_Data!B:B,A17) -> 64.416667 | F17: =AVERAGEIFS(Correlation_Data!O:O,Correlation_Data!B:B,A17) -> 76.916667 | G17: =AVERAGEIFS(Correlation_Data!Q:Q,Correlation_Data!B:B,A17) -> 0.82228322 | H17: =AVERAGEIFS(Correlation_Data!T:T,Correlation_Data!B:B,A17) -> 78.35
A18: Retail | B18: =AVERAGEIFS(Correlation_Data!G:G,Correlation_Data!B:B,A18) -> 64.75 | C18: =AVERAGEIFS(Correlation_Data!C:C,Correlation_Data!B:B,A18) -> 0.019634332 | D18: =AVERAGEIFS(Correlation_Data!F:F,Correlation_Data!B:B,A18) -> 0.85904711 | E18: =AVERAGEIFS(Correlation_Data!M:M,Correlation_Data!B:B,A18) -> 65.916667 | F18: =AVERAGEIFS(Correlation_Data!O:O,Correlation_Data!B:B,A18) -> 79.5 | G18: =AVERAGEIFS(Correlation_Data!Q:Q,Correlation_Data!B:B,A18) -> 0.81930701 | H18: =AVERAGEIFS(Correlation_Data!T:T,Correlation_Data!B:B,A18) -> 78.566667
A19: Facilities | B19: =AVERAGEIFS(Correlation_Data!G:G,Correlation_Data!B:B,A19) -> 64 | C19: =AVERAGEIFS(Correlation_Data!C:C,Correlation_Data!B:B,A19) -> 0.016008899 | D19: =AVERAGEIFS(Correlation_Data!F:F,Correlation_Data!B:B,A19) -> 0.79012078 | E19: =AVERAGEIFS(Correlation_Data!M:M,Correlation_Data!B:B,A19) -> 64.25 | F19: =AVERAGEIFS(Correlation_Data!O:O,Correlation_Data!B:B,A19) -> 70.083333 | G19: =AVERAGEIFS(Correlation_Data!Q:Q,Correlation_Data!B:B,A19) -> 0.78138254 | H19: =AVERAGEIFS(Correlation_Data!T:T,Correlation_Data!B:B,A19) -> 77.616667
A20: Security | B20: =AVERAGEIFS(Correlation_Data!G:G,Correlation_Data!B:B,A20) -> 67.75 | C20: =AVERAGEIFS(Correlation_Data!C:C,Correlation_Data!B:B,A20) -> 0.01576945 | D20: =AVERAGEIFS(Correlation_Data!F:F,Correlation_Data!B:B,A20) -> 0.79366709 | E20: =AVERAGEIFS(Correlation_Data!M:M,Correlation_Data!B:B,A20) -> 67.083333 | F20: =AVERAGEIFS(Correlation_Data!O:O,Correlation_Data!B:B,A20) -> 79.666667 | G20: =AVERAGEIFS(Correlation_Data!Q:Q,Correlation_Data!B:B,A20) -> 0.84204356 | H20: =AVERAGEIFS(Correlation_Data!T:T,Correlation_Data!B:B,A20) -> 78.758333
A21: Finance | B21: =AVERAGEIFS(Correlation_Data!G:G,Correlation_Data!B:B,A21) -> 66.166667 | C21: =AVERAGEIFS(Correlation_Data!C:C,Correlation_Data!B:B,A21) -> 0.015627515 | D21: =AVERAGEIFS(Correlation_Data!F:F,Correlation_Data!B:B,A21) -> 0.83300855 | E21: =AVERAGEIFS(Correlation_Data!M:M,Correlation_Data!B:B,A21) -> 65.666667 | F21: =AVERAGEIFS(Correlation_Data!O:O,Correlation_Data!B:B,A21) -> 72.166667 | G21: =AVERAGEIFS(Correlation_Data!Q:Q,Correlation_Data!B:B,A21) -> 0.79875144 | H21: =AVERAGEIFS(Correlation_Data!T:T,Correlation_Data!B:B,A21) -> 79.916667
A22: HR | B22: =AVERAGEIFS(Correlation_Data!G:G,Correlation_Data!B:B,A22) -> 68.166667 | C22: =AVERAGEIFS(Correlation_Data!C:C,Correlation_Data!B:B,A22) -> 0.019779202 | D22: =AVERAGEIFS(Correlation_Data!F:F,Correlation_Data!B:B,A22) -> 0.79938806 | E22: =AVERAGEIFS(Correlation_Data!M:M,Correlation_Data!B:B,A22) -> 66 | F22: =AVERAGEIFS(Correlation_Data!O:O,Correlation_Data!B:B,A22) -> 72.083333 | G22: =AVERAGEIFS(Correlation_Data!Q:Q,Correlation_Data!B:B,A22) -> 0.79703037 | H22: =AVERAGEIFS(Correlation_Data!T:T,Correlation_Data!B:B,A22) -> 78.483333
A23: Marketing | B23: =AVERAGEIFS(Correlation_Data!G:G,Correlation_Data!B:B,A23) -> 63.083333 | C23: =AVERAGEIFS(Correlation_Data!C:C,Correlation_Data!B:B,A23) -> 0.014215478 | D23: =AVERAGEIFS(Correlation_Data!F:F,Correlation_Data!B:B,A23) -> 0.77863703 | E23: =AVERAGEIFS(Correlation_Data!M:M,Correlation_Data!B:B,A23) -> 66.083333 | F23: =AVERAGEIFS(Correlation_Data!O:O,Correlation_Data!B:B,A23) -> 68.583333 | G23: =AVERAGEIFS(Correlation_Data!Q:Q,Correlation_Data!B:B,A23) -> 0.78367499 | H23: =AVERAGEIFS(Correlation_Data!T:T,Correlation_Data!B:B,A23) -> 77.65
A24: IT | B24: =AVERAGEIFS(Correlation_Data!G:G,Correlation_Data!B:B,A24) -> 66.25 | C24: =AVERAGEIFS(Correlation_Data!C:C,Correlation_Data!B:B,A24) -> 0.016080521 | D24: =AVERAGEIFS(Correlation_Data!F:F,Correlation_Data!B:B,A24) -> 0.8182676 | E24: =AVERAGEIFS(Correlation_Data!M:M,Correlation_Data!B:B,A24) -> 66.5 | F24: =AVERAGEIFS(Correlation_Data!O:O,Correlation_Data!B:B,A24) -> 71.25 | G24: =AVERAGEIFS(Correlation_Data!Q:Q,Correlation_Data!B:B,A24) -> 0.79242273 | H24: =AVERAGEIFS(Correlation_Data!T:T,Correlation_Data!B:B,A24) -> 79.208333
A25: Operations | B25: =AVERAGEIFS(Correlation_Data!G:G,Correlation_Data!B:B,A25) -> 66 | C25: =AVERAGEIFS(Correlation_Data!C:C,Correlation_Data!B:B,A25) -> 0.01411384 | D25: =AVERAGEIFS(Correlation_Data!F:F,Correlation_Data!B:B,A25) -> 0.82462057 | E25: =AVERAGEIFS(Correlation_Data!M:M,Correlation_Data!B:B,A25) -> 67.583333 | F25: =AVERAGEIFS(Correlation_Data!O:O,Correlation_Data!B:B,A25) -> 78.583333 | G25: =AVERAGEIFS(Correlation_Data!Q:Q,Correlation_Data!B:B,A25) -> 0.81492771 | H25: =AVERAGEIFS(Correlation_Data!T:T,Correlation_Data!B:B,A25) -> 79.325
A26: Customer Experience | B26: =AVERAGEIFS(Correlation_Data!G:G,Correlation_Data!B:B,A26) -> 59.75 | C26: =AVERAGEIFS(Correlation_Data!C:C,Correlation_Data!B:B,A26) -> 0.022623356 | D26: =AVERAGEIFS(Correlation_Data!F:F,Correlation_Data!B:B,A26) -> 0.77163588 | E26: =AVERAGEIFS(Correlation_Data!M:M,Correlation_Data!B:B,A26) -> 62.5 | F26: =AVERAGEIFS(Correlation_Data!O:O,Correlation_Data!B:B,A26) -> 74.75 | G26: =AVERAGEIFS(Correlation_Data!Q:Q,Correlation_Data!B:B,A26) -> 0.81200746 | H26: =AVERAGEIFS(Correlation_Data!T:T,Correlation_Data!B:B,A26) -> 76.633333
A29: Recommended Sindibad Insight | B29: Trigger | C29: Suggested Action
A30: Frontline instability is affecting service quality | B30: Turnover > average and complaints rising | C30: Prioritise retention actions in customer-facing departments
A31: Brand risk may be internal before external | B31: Engagement and advocacy below target | C31: Launch EVP refresh and internal communication campaign
A32: Financial pressure is partly people-driven | B32: Overtime cost linked to absence and vacancies | C32: Improve workforce planning and reduce absence hotspots
A33: ISO evidence gap remains in skills and succession | B33: Evidence completeness below 75% | C33: Complete LMS evidence and critical role successor register
A34: Leadership should review low HC Impact departments | B34: HC Impact score below 70 | C34: Assign owners for corrective actions and track monthly

Sheet Lists
A1: Departments | B1: Grades | C1: Nationalities | D1: Gender | E1: Contract Types
A2: Hospitality | B2: G1 | C2: Qatari | D2: Female | E2: Permanent
A3: Retail | B3: G2 | C3: Lebanese | D3: Male | E3: Fixed-term
A4: Facilities | B4: G3 | C4: Indian | E4: Outsourced
A5: Security | B5: G4 | C5: Filipino | E5: Consultant
A6: Finance | B6: G5 | C6: Nepali
A7: HR | B7: M1 | C7: Egyptian
A8: Marketing | B8: M2 | C8: Jordanian
A9: IT | B9: D1 | C9: Sri Lankan
A10: Operations | C10: Pakistani
A11: Customer Experience | C11: Tunisian
C12: Moroccan
C13: Kenyan
C14: British
